aws_lambda_types/__init__.py
aws_lambda_types/alb.py
aws_lambda_types/api_gw.py
aws_lambda_types/event_bridge.py
aws_lambda_types/http.py
aws_lambda_types/sns.py
aws_lambda_types/sqs.py
aws_lambda_types-0.2.1.dist-info/LICENSE
aws_lambda_types-0.2.1.dist-info/WHEEL
aws_lambda_types-0.2.1.dist-info/METADATA
aws_lambda_types-0.2.1.dist-info/RECORD
