Metadata-Version: 2.1
Name: aws-lambda-types
Version: 0.2.1
Summary: Type definitions for AWS Lambda events using Python type hinting.
Home-page: https://github.com/emcpow2/aws-lambda-py-types
License: MIT
Author: Eduard Iskandarov
Author-email: eduard.iskandarov@yandex.ru
Requires-Python: >=3.6.1,<4.0.0
Classifier: License :: OSI Approved :: MIT License
Classifier: Programming Language :: Python :: 3
Classifier: Programming Language :: Python :: 3.7
Classifier: Programming Language :: Python :: 3.8
Classifier: Programming Language :: Python :: 3.9
Requires-Dist: typing-extensions (>=3.7.4,<4.0.0)
Project-URL: Repository, https://github.com/emcpow2/aws-lambda-py-types
